iCLIPS-0.3.0.data/data/share/jupyter/kernels/clips/kernel.css
iCLIPS-0.3.0.data/data/share/jupyter/kernels/clips/kernel.js
iCLIPS-0.3.0.data/data/share/jupyter/kernels/clips/kernel.json
iclips/__init__.py
iclips/__main__.py
iclips/clips_kernel.py
iclips/clips_pygments.py
iclips/common.py
iCLIPS-0.3.0.dist-info/METADATA
iCLIPS-0.3.0.dist-info/WHEEL
iCLIPS-0.3.0.dist-info/entry_points.txt
iCLIPS-0.3.0.dist-info/top_level.txt
iCLIPS-0.3.0.dist-info/RECORD
