Metadata-Version: 2.1
Name: iCLIPS
Version: 0.3.0
Summary: CLIPS Jupyter console
Home-page: https://github.com/noxdafox/iclips
Author: Matteo Cafasso
Author-email: noxdafox@gmail.com
License: GPL
Keywords: clips expert-system jupyter
Classifier: Programming Language :: Python
Classifier: Development Status :: 3 - Alpha
Classifier: Intended Audience :: Developers
Classifier: License :: OSI Approved :: GNU General Public License v3 or later (GPLv3+)
Requires-Dist: regex
Requires-Dist: clipspy >=1.0.0
Requires-Dist: jupyter-console
